footpy_manager
