Metadata-Version: 2.1
Name: footpy-manager
Version: 0.5
Summary: A Python package to manage matches of football.
Home-page: UNKNOWN
License: UNKNOWN
Platform: UNKNOWN
